omni_pro_base/__init__.py
omni_pro_base/apps.py
omni_pro_base/mig_settings.py
omni_pro_base/setting.py
omni_pro_base/urls.py
omni_pro_base/admin/__init__.py
omni_pro_base/admin/auth.py
omni_pro_base/admin/base_admin.py
omni_pro_base/admin/users.py
omni_pro_base/forms/__init__.py
omni_pro_base/forms/users.py
omni_pro_base/migrations/0001_initial.py
omni_pro_base/migrations/__init__.py
omni_pro_base/models/__init__.py
omni_pro_base/models/base_model.py
omni_pro_base/models/users.py
omni_pro_base/serializers/__init__.py
omni_pro_base/serializers/users.py
omni_pro_base/static/vendor/omni/css/main.css
omni_pro_base/static/vendor/omni/img/favicon.ico
omni_pro_base/static/vendor/omni/img/logo.svg
omni_pro_base/static/vendor/omni/img/logo_login.svg
omni_pro_base/static/vendor/omni/js/main.js
omni_pro_base/tests/__init__.py
omni_pro_base/views/__init__.py
omni_pro_base/views/users.py
omni_pro_app_base-0.0.5.dist-info/LICENSE
omni_pro_app_base-0.0.5.dist-info/METADATA
omni_pro_app_base-0.0.5.dist-info/WHEEL
omni_pro_app_base-0.0.5.dist-info/top_level.txt
omni_pro_app_base-0.0.5.dist-info/RECORD
