Metadata-Version: 2.1
Name: omni-pro-app-base
Version: 0.0.5
Summary: Python library designed to be a apps for OMS Django apps.
Home-page: https://github.com/Omnipro-Solutions/saas-app-base
Author: OMNI.PRO
Author-email: development@omni.pro
License: MIT
Classifier: Development Status :: 3 - Alpha
Classifier: Intended Audience :: Developers
Classifier: License :: OSI Approved :: MIT License
Classifier: Programming Language :: Python :: 3.11
Requires-Python: >=3.11
License-File: LICENSE
Requires-Dist: Django ==5.0
Requires-Dist: environs ==9.5.0
Requires-Dist: django-jazzmin ==2.6.0
Requires-Dist: djangorestframework ==3.14.0
Requires-Dist: django-oauth-toolkit ==2.3.0
Provides-Extra: dev
Requires-Dist: pytest ; extra == 'dev'
